permutive/__init__.py
permutive/base.py
permutive/event.py
permutive/exceptions.py
permutive/user.py
permutive/util.py
permutive-0.7.0.dist-info/DESCRIPTION.rst
permutive-0.7.0.dist-info/METADATA
permutive-0.7.0.dist-info/RECORD
permutive-0.7.0.dist-info/WHEEL
permutive-0.7.0.dist-info/metadata.json
permutive-0.7.0.dist-info/top_level.txt
