Metadata-Version: 2.0
Name: permutive
Version: 0.7.0
Summary: Python wrapper for Permutive API
Home-page: https://github.com/tailsdotcom/permutive-sdk
Author: Dinesh Vitharanage
Author-email: dvitharanage@gmail.com
License: MIT license
Keywords: permutive
Platform: UNKNOWN
Classifier: Development Status :: 2 - Pre-Alpha
Classifier: Intended Audience :: Developers
Classifier: License :: OSI Approved :: MIT License
Classifier: Natural Language :: English
Classifier: Programming Language :: Python :: 2
Classifier: Programming Language :: Python :: 2.6
Classifier: Programming Language :: Python :: 2.7
Classifier: Programming Language :: Python :: 3
Classifier: Programming Language :: Python :: 3.3
Classifier: Programming Language :: Python :: 3.4
Classifier: Programming Language :: Python :: 3.5
Requires-Dist: arrow
Requires-Dist: requests
